primate/typing.py
primate/fttr.cpython-313-x86_64-linux-gnu.so
primate/lanczos.py
primate/tridiag.py
primate/linalg.py
primate/stats.py
primate/random.py
primate/__init__.py
primate/tqli.py
primate/tqli.cpython-313-x86_64-linux-gnu.so
primate/trace.py
primate/plotting.py
primate/fttr.py
primate/integrate.py
primate/operators.py
primate/_lanczos.cpython-313-x86_64-linux-gnu.so
primate/estimators.py
primate/diagonal.py
primate/special.py
primate/include/linear_operator.h
primate/include/lanczos.h
primate/include/pylinop.h
scikit_primate-0.5.6.dist-info/RECORD
scikit_primate-0.5.6.dist-info/LICENSE
scikit_primate-0.5.6.dist-info/METADATA
scikit_primate-0.5.6.dist-info/WHEEL
