Metadata-Version: 2.1
Name: scikit-primate
Version: 0.5.6
Summary: Package for implicit matrix function, trace, and diagonal estimation.
Author-Email: Matt Piekenbrock <matt.piekenbrock@gmail.com>
License:                                  Apache License
Classifier: Development Status :: 3 - Alpha
Classifier: Intended Audience :: Science/Research
Classifier: License :: OSI Approved :: Apache Software License
Classifier: Operating System :: OS Independent
Classifier: Programming Language :: Python
Classifier: Programming Language :: Python :: 3
Classifier: Programming Language :: Python :: 3 :: Only
Classifier: Programming Language :: Python :: 3.9
Classifier: Programming Language :: Python :: 3.10
Classifier: Programming Language :: Python :: 3.11
Classifier: Programming Language :: Python :: 3.12
Classifier: Programming Language :: Python :: 3.13
Requires-Python: >=3.8
Requires-Dist: numpy
Requires-Dist: scipy
Provides-Extra: test
Requires-Dist: pytest; extra == "test"
Requires-Dist: pytest-cov; extra == "test"
Requires-Dist: pytest-benchmark; extra == "test"
Requires-Dist: coverage>=7.2.0; extra == "test"
Provides-Extra: doc
Requires-Dist: quartodoc; extra == "doc"
Provides-Extra: dev
Requires-Dist: meson-python; extra == "dev"
Requires-Dist: pybind11; extra == "dev"
Requires-Dist: numpy; extra == "dev"
